aiorchestra_asyncssh_plugin-0.1.2.dist-info/DESCRIPTION.rst
aiorchestra_asyncssh_plugin-0.1.2.dist-info/METADATA
aiorchestra_asyncssh_plugin-0.1.2.dist-info/RECORD
aiorchestra_asyncssh_plugin-0.1.2.dist-info/WHEEL
aiorchestra_asyncssh_plugin-0.1.2.dist-info/metadata.json
aiorchestra_asyncssh_plugin-0.1.2.dist-info/top_level.txt
aiorchestra_asyncssh_plugin-0.1.2.dist-info/zip-safe
asyncssh_plugin/__init__.py
asyncssh_plugin/tasks.py
asyncssh_plugin/tests/__init__.py
asyncssh_plugin/tests/config.py
asyncssh_plugin/tests/plugin.py
asyncssh_plugin/tests/integration/__init__.py
asyncssh_plugin/tests/integration/test_async_software_configuration.py
