Metadata-Version: 2.0
Name: aiorchestra-asyncssh-plugin
Version: 0.1.2
Summary: AsyncIO TOSCA orchestrator AsyncSSH plugin for Software configuration
Home-page: https://aiorchestra.io/
Author: Denys Makogon
Author-email: lildee1991@gmail.com
License: License :: OSI Approved :: Apache Software License
Keywords: orchestration,python,framework,asyncio,uvloop,AsyncSSH
Platform: Linux
Platform: Mac OS-X
Platform: Unix
Classifier: License :: OSI Approved :: Apache Software License
Classifier: Intended Audience :: Information Technology
Classifier: Intended Audience :: System Administrators
Classifier: Intended Audience :: Developers
Classifier: Environment :: No Input/Output (Daemon)
Classifier: Programming Language :: Python :: 3.5
Classifier: Topic :: Software Development :: Libraries :: Python Modules
Classifier: Topic :: System :: Distributed Computing
Classifier: Operating System :: Microsoft :: Windows
Classifier: Operating System :: POSIX
Classifier: Operating System :: Unix
Classifier: Operating System :: MacOS
Requires-Dist: aiorchestra (==0.1.2)
Requires-Dist: asyncssh
